fetch_bduss_id/__init__.py
fetch_bduss_id/fetch_bduss_id.py
fetch_bduss_baiduid-0.0.1.dist-info/LICENSE
fetch_bduss_baiduid-0.0.1.dist-info/METADATA
fetch_bduss_baiduid-0.0.1.dist-info/WHEEL
fetch_bduss_baiduid-0.0.1.dist-info/top_level.txt
fetch_bduss_baiduid-0.0.1.dist-info/RECORD
