Metadata-Version: 2.1
Name: fetch-bduss-baiduid
Version: 0.0.1
Summary: 获取 BDUSS 和 BAIDUID
Home-page: http://github.com/ffreemt/fetch-bduss-baiduid
Author: mikeee
License: MIT License
Download-URL: https://github.com/ffreemt/fetch-bduss-baiduid/archive/v_001.tar.gz
Keywords: machine translation,free,async
Platform: UNKNOWN
Classifier: Development Status :: 3 - Alpha
Classifier: Intended Audience :: Developers
Classifier: Programming Language :: Python :: 3
Classifier: Programming Language :: Python :: 3.6
Classifier: License :: OSI Approved :: MIT License
Requires-Dist: browser-cookie3
Requires-Dist: pyperclip
Requires-Dist: logzero
